MANIFEST.in
README.rst
ralc.py
setup.py
ralc.egg-info/PKG-INFO
ralc.egg-info/SOURCES.txt
ralc.egg-info/dependency_links.txt
ralc.egg-info/entry_points.txt
ralc.egg-info/top_level.txt