Metadata-Version: 1.1
Name: ralc
Version: 0.1
Summary: Rate Calculator.
Home-page: https://github.com/playpauseandstop/ralc
Author: Igor Davydenko
Author-email: playpauseandstop@gmail.com
License: BSD License
Platform: any
Classifier: Development Status :: 4 - Beta
Classifier: Intended Audience :: Developers
Classifier: Intended Audience :: System Administrators
Classifier: License :: OSI Approved :: BSD License
Classifier: Operating System :: OS Independent
Classifier: Programming Language :: Python :: 2.6
Classifier: Programming Language :: Python :: 2.7
Classifier: Programming Language :: Python :: 3.2
Classifier: Programming Language :: Python :: 3.3
Classifier: Programming Language :: Python :: Implementation :: PyPy
